__init__.py
optimal_voting/OptimizableRule.py
optimal_voting/__init__.py
optimal_voting/annealing_experiments.py
optimal_voting/data_utils.py
optimal_voting/evaluation.py
optimal_voting/gradient_descent.py
optimal_voting/mixed_integer_optimization.py
optimal_voting/voting_utils.py
optimal_voting-0.0.8.dist-info/licenses/LICENSE
optimal_voting-0.0.8.dist-info/METADATA
optimal_voting-0.0.8.dist-info/WHEEL
optimal_voting-0.0.8.dist-info/top_level.txt
optimal_voting-0.0.8.dist-info/RECORD
