Metadata-Version: 2.4
Name: optimal-voting
Version: 0.0.8
Summary: Functionality to optimize different classes of voting rules for user-defined goals.
Author-email: Ben Armstrong <research@benarmstrong.ca>
License: MIT License
Project-URL: Repository, https://github.com/beng341/optimal_voting
Keywords: social choice,voting,optimization,scoring rule
Requires-Python: >=3.9.6
License-File: LICENSE
Requires-Dist: requests>=2.25.0
Requires-Dist: numpy>=1.26.4
Requires-Dist: pandas>=2.2.2
Requires-Dist: abcvoting>=2.10.0
Requires-Dist: pref-voting>=1.13.18
Requires-Dist: seaborn>=0.13.2
Requires-Dist: simanneal>=0.5.0
Dynamic: license-file
